plone.app.dexterity-4.1.1-py3.13-nspkg.pth
plone/app/dexterity/TODO.txt
plone/app/dexterity/__init__.py
plone/app/dexterity/configure.zcml
plone/app/dexterity/events.zcml
plone/app/dexterity/factories.py
plone/app/dexterity/interfaces.py
plone/app/dexterity/meta.zcml
plone/app/dexterity/overrides.zcml
plone/app/dexterity/permissions.py
plone/app/dexterity/serialize.py
plone/app/dexterity/testing.py
plone/app/dexterity/behaviors/__init__.py
plone/app/dexterity/behaviors/configure.zcml
plone/app/dexterity/behaviors/constrains.py
plone/app/dexterity/behaviors/discussion.py
plone/app/dexterity/behaviors/exclfromnav.py
plone/app/dexterity/behaviors/filename.py
plone/app/dexterity/behaviors/id.py
plone/app/dexterity/behaviors/metadata.py
plone/app/dexterity/behaviors/nextprevious.py
plone/app/dexterity/behaviors/related.py
plone/app/dexterity/behaviors/tests/__init__.py
plone/app/dexterity/behaviors/tests/test_contrains.py
plone/app/dexterity/behaviors/tests/test_id.py
plone/app/dexterity/behaviors/tests/test_metadata.py
plone/app/dexterity/browser/__init__.py
plone/app/dexterity/browser/add_type.py
plone/app/dexterity/browser/behaviors.pt
plone/app/dexterity/browser/behaviors.py
plone/app/dexterity/browser/blank.css
plone/app/dexterity/browser/clone_type.py
plone/app/dexterity/browser/configure.zcml
plone/app/dexterity/browser/container.pt
plone/app/dexterity/browser/export.py
plone/app/dexterity/browser/fields.py
plone/app/dexterity/browser/folder_listing.pt
plone/app/dexterity/browser/folder_listing.py
plone/app/dexterity/browser/import_types.py
plone/app/dexterity/browser/item.pt
plone/app/dexterity/browser/layout.py
plone/app/dexterity/browser/modeleditor.pt
plone/app/dexterity/browser/modeleditor.py
plone/app/dexterity/browser/overview.pt
plone/app/dexterity/browser/overview.py
plone/app/dexterity/browser/tabbed_forms.pt
plone/app/dexterity/browser/types.py
plone/app/dexterity/browser/types_listing.pt
plone/app/dexterity/browser/types_listing_row.pt
plone_app_dexterity-4.1.1.dist-info/METADATA
plone_app_dexterity-4.1.1.dist-info/WHEEL
plone_app_dexterity-4.1.1.dist-info/entry_points.txt
plone_app_dexterity-4.1.1.dist-info/namespace_packages.txt
plone_app_dexterity-4.1.1.dist-info/top_level.txt
plone_app_dexterity-4.1.1.dist-info/RECORD
