Metadata-Version: 2.4
Name: plone.app.dexterity
Version: 4.1.1
Summary: Dexterity is a content type framework for CMF  applications, with particular emphasis on Plone. It can be viewed as an alternative to Archetypes that is more light-weight and modular.
Home-page: http://plone.org/products/dexterity
Author: Martin Aspeli, David Glick, et al
Author-email: dexterity-development@googlegroups.com
License: GPL
Keywords: plone ttw dexterity schema interface
Classifier: Development Status :: 5 - Production/Stable
Classifier: Environment :: Web Environment
Classifier: Framework :: Plone
Classifier: Framework :: Plone :: 6.1
Classifier: Framework :: Plone :: Core
Classifier: Framework :: Zope :: 5
Classifier: License :: OSI Approved :: GNU General Public License v2 (GPLv2)
Classifier: Operating System :: OS Independent
Classifier: Programming Language :: Python
Classifier: Programming Language :: Python :: 3.10
Classifier: Programming Language :: Python :: 3.11
Classifier: Programming Language :: Python :: 3.12
Requires-Python: >=3.10
Requires-Dist: plone.app.textfield
Requires-Dist: plone.behavior>=1.0
Requires-Dist: plone.dexterity>=2.2.2
Requires-Dist: plone.formwidget.namedfile
Requires-Dist: plone.namedfile>=1.0.0
Requires-Dist: plone.rfc822
Requires-Dist: plone.schemaeditor>1.3.3
Requires-Dist: lxml
Requires-Dist: plone.base
Requires-Dist: plone.app.uuid
Requires-Dist: plone.app.z3cform>=4.6.0
Requires-Dist: plone.autoform>=1.1
Requires-Dist: plone.contentrules
Requires-Dist: plone.portlets
Requires-Dist: plone.schema>=1.1.0
Requires-Dist: plone.supermodel>=1.1
Requires-Dist: plone.z3cform>=0.6.0
Requires-Dist: Products.GenericSetup
Requires-Dist: setuptools
Requires-Dist: Zope
Requires-Dist: zope.browserpage
Requires-Dist: z3c.form>=3.0.0
Requires-Dist: Products.statusmessages
Requires-Dist: plone.app.vocabularies
Requires-Dist: plone.indexer
Requires-Dist: plone.locking
Requires-Dist: plone.registry
Requires-Dist: plone.uuid
Requires-Dist: zope.cachedescriptors
Requires-Dist: zope.dottedname
Requires-Dist: zope.filerepresentation
Provides-Extra: test
Requires-Dist: plone.app.robotframework; extra == "test"
Requires-Dist: plone.app.testing; extra == "test"
Requires-Dist: plone.i18n; extra == "test"
Requires-Dist: plone.testing; extra == "test"
Requires-Dist: robotsuite; extra == "test"
Requires-Dist: plone.api; extra == "test"
Provides-Extra: grok
Requires-Dist: five.grok; extra == "grok"
Requires-Dist: plone.directives.dexterity; extra == "grok"
Requires-Dist: plone.directives.form>=1.1; extra == "grok"
Provides-Extra: relations
Requires-Dist: plone.app.relationfield; extra == "relations"
Requires-Dist: plone.app.intid; extra == "relations"
Requires-Dist: z3c.relationfield; extra == "relations"
Dynamic: author
Dynamic: author-email
Dynamic: classifier
Dynamic: description
Dynamic: description-content-type
Dynamic: home-page
Dynamic: keywords
Dynamic: license
Dynamic: provides-extra
Dynamic: requires-dist
Dynamic: requires-python
Dynamic: summary
